colour_stacking/__init__.py
colour_stacking/__main__.py
colour_stacking/input.py
colour_stacking/input_config.py
colour_stacking/models.py
colour_stacking/solver.py
colour_stacking-0.3.dist-info/LICENSE
colour_stacking-0.3.dist-info/METADATA
colour_stacking-0.3.dist-info/WHEEL
colour_stacking-0.3.dist-info/top_level.txt
colour_stacking-0.3.dist-info/RECORD
