Metadata-Version: 2.1
Name: colour-stacking
Version: 0.3
Summary: Optimisation of coloured line thickness when displaying maps
Home-page: https://www.gitlab.com/jbrobertson/colour-stacking
Author: JB Robertson
Author-email: jbr@freeshell.org
License: UNKNOWN
Platform: UNKNOWN
Classifier: Programming Language :: Python :: 3
Classifier: License :: OSI Approved :: MIT License
Classifier: Operating System :: OS Independent
Requires-Python: >=3.6
Requires-Dist: z3-solver (==4.8.9.0)
Requires-Dist: pydantic (==1.7.2)
Requires-Dist: shapely (==1.7.1)
